capturemock/CaptureMock.spec
capturemock/__init__.py
capturemock/amqptraffic.py
capturemock/binarytcptraffic.py
capturemock/capturecommand.py
capturemock/capturemock_intercept.exe
capturemock/capturepython.py
capturemock/clientservertraffic.py
capturemock/cmdlineutils.py
capturemock/commandlinetraffic.py
capturemock/config.py
capturemock/customtraffic.py
capturemock/encodingutils.py
capturemock/fileedittraffic.py
capturemock/ftptraffic.py
capturemock/id_mapping.py
capturemock/python_script.exe
capturemock/pythonclient.py
capturemock/pythontraffic.py
capturemock/recordfilehandler.py
capturemock/replayinfo.py
capturemock/server.py
capturemock/traffic.py
capturemock/__pycache__/__init__.cpython-311.pyc
capturemock/__pycache__/__init__.cpython-312.pyc
capturemock/__pycache__/__init__.cpython-313.pyc
capturemock/__pycache__/amqptraffic.cpython-313.pyc
capturemock/__pycache__/binarytcptraffic.cpython-313.pyc
capturemock/__pycache__/capturecommand.cpython-311.pyc
capturemock/__pycache__/capturecommand.cpython-312.pyc
capturemock/__pycache__/capturecommand.cpython-313.pyc
capturemock/__pycache__/capturepython.cpython-311.pyc
capturemock/__pycache__/capturepython.cpython-312.pyc
capturemock/__pycache__/capturepython.cpython-313.pyc
capturemock/__pycache__/clientservertraffic.cpython-311.pyc
capturemock/__pycache__/clientservertraffic.cpython-313.pyc
capturemock/__pycache__/cmdlineutils.cpython-311.pyc
capturemock/__pycache__/cmdlineutils.cpython-312.pyc
capturemock/__pycache__/cmdlineutils.cpython-313.pyc
capturemock/__pycache__/commandlinetraffic.cpython-311.pyc
capturemock/__pycache__/commandlinetraffic.cpython-313.pyc
capturemock/__pycache__/config.cpython-311.pyc
capturemock/__pycache__/config.cpython-312.pyc
capturemock/__pycache__/config.cpython-313.pyc
capturemock/__pycache__/customtraffic.cpython-311.pyc
capturemock/__pycache__/customtraffic.cpython-313.pyc
capturemock/__pycache__/encodingutils.cpython-311.pyc
capturemock/__pycache__/encodingutils.cpython-313.pyc
capturemock-2.8.3.dist-info/METADATA
capturemock-2.8.3.dist-info/WHEEL
capturemock-2.8.3.dist-info/entry_points.txt
capturemock-2.8.3.dist-info/top_level.txt
capturemock-2.8.3.dist-info/RECORD
