Metadata-Version: 2.4
Name: CaptureMock
Version: 2.8.3
Summary: A tool for creating mocks via a capture-replay style approach
Author-email: Geoff Bache <geoff.bache@pobox.com>
Project-URL: Homepage, http://www.texttest.org/index.php?page=capturemock
Project-URL: Documentation, http://www.texttest.org/index.php?page=capturemock
Project-URL: Repository, https://github.com/texttest/capturemock
Project-URL: Issues, https://github.com/texttest/capturemock/issues/
Classifier: Development Status :: 5 - Production/Stable
Classifier: Environment :: Console
Classifier: Intended Audience :: Developers
Classifier: Intended Audience :: Information Technology
Classifier: License :: OSI Approved :: GNU Library or Lesser General Public License (LGPL)
Classifier: Operating System :: OS Independent
Classifier: Programming Language :: Python
Classifier: Topic :: Software Development :: Libraries :: Python Modules
Classifier: Topic :: Software Development :: Testing
Requires-Python: >=3.9
